Workbook

Sheet Budget
A1: Devil's Night · AFTERIMAGE 001 — budget
A2: Fri 30 Oct 2026 · Rio · doors 9 · close 2. Prices before tax, seen 1–5 Oct 2026. Blue = inputs, green = from other tabs.
A4: Crew | B4: 6
A5: Each puts in | B5: 176
A6: Pool | B6: =B4*B5 -> 1056
A8: Line | B8: $ | C8: Note
A9: he/they (co.b_nguyen b2b Nioon) | B9: 300 | C9: Confirmed
A10: Rohan Rali | B10: 275 | C10: Confirmed 5 Oct
A11: Glamz | B11: 0 | C11: NOT confirmed — not budgeted
A12: Drinks | B12: =Drinks!F19 -> 211.5896 | C12: 2 JJs + cans + soju
A13: Ice | B13: =SUMIF('Ice & Cups'!H7:H11,"Y",'Ice & Cups'!G7:G11) -> 24 | C13: Picked source
A14: Cups | B14: =SUMIF('Ice & Cups'!H17:H21,"Y",'Ice & Cups'!G17:G21) -> 22.56 | C14: Picked source
A15: Water, napkins, dispensers | B15: =SUMIF('Ice & Cups'!H25:H28,"Y",'Ice & Cups'!G25:G28) -> 69.52
A16: Decor | B16: =Decor!G14 -> 181.65 | C16: Retail vs eBay best picks
A17: DIY at the maker space | B17: ='DIY (Maker)'!D10 -> 58 | C17: EST materials
A18: Smoking spot | B18: =Smoking!E9 -> 36.26
A19: Food | B19: 0 | C19: TBD
A20: CDJ backup (Rock n Roll Rentals) | B20: 0 | C20: $375/weekend only if Rapid Ric falls through
A21: Party total | B21: =SUM(B9:B20) -> 1178.5796
A22: Left in pool | B22: =B6-B21 -> -122.5796
A24: Cap 01 (separate — merch) | B24: =Hats!B15 -> 429.36 | C24: Route picked on Hats tab
A25: Left if the pool also pays caps | B25: =B22-B24 -> -551.9396
A27: Guest drinks covered | B27: =Drinks!B33 -> 1.0290444 | C27: Our drinks vs guests × drinks each (Drinks tab)

Sheet Drinks
A1: Drinks · 2 jungle juices + cans
A2: Blue = inputs you can change. Std drink = 0.6 oz alcohol. BYOB tops up the rest.
A4: Item | B4: Group | C4: Store | D4: Qty | E4: Unit $ | F4: Cost | G4: Oz each | H4: ABV | I4: Std drinks | J4: Guest? | K4: Note / link
A5: Svedka vodka 1.75 L | B5: Vodka JJ | C5: Twin Liquors | D5: 1 | E5: 18.99 | F5: =D5*E5 -> 18.99 | G5: 59.2 | H5: 0.4 | I5: =D5*G5*H5/0.6 -> 39.466667 | J5: Y | K5: https://twinliquors.com/shop/product/svedka-80-proof-vodka/564bd7e469702d5e6e6e0000
A6: Hawaiian Punch 1 gal | B6: Vodka JJ | C6: H-E-B | D6: 1 | E6: 3.22 | F6: =D6*E6 -> 3.22 | G6: 128 | H6: 0 | I6: =D6*G6*H6/0.6 -> 0 | J6: Y | K6: H-E-B
A7: Pineapple juice 64 oz | B7: Vodka JJ | C7: H-E-B | D7: 1 | E7: 4.27 | F7: =D7*E7 -> 4.27 | G7: 64 | H7: 0 | I7: =D7*G7*H7/0.6 -> 0 | J7: Y | K7: H-E-B
A8: Sprite 2 L | B8: Vodka JJ | C8: H-E-B | D8: 1 | E8: 2.97 | F8: =D8*E8 -> 2.97 | G8: 67.6 | H8: 0 | I8: =D8*G8*H8/0.6 -> 0 | J8: Y | K8: H-E-B
A9: Lunazul Blanco tequila 1.75 L | B9: Tequila JJ | C9: Twin Liquors | D9: 1 | E9: 36.99 | F9: =D9*E9 -> 36.99 | G9: 59.2 | H9: 0.4 | I9: =D9*G9*H9/0.6 -> 39.466667 | J9: Y | K9: https://twinliquors.com/ (Lunazul 1.75 L)
A10: DeKuyper Triple Sec 1 L (16 oz used) | B10: Tequila JJ | C10: Twin Liquors | D10: 1 | E10: 7.99 | F10: =D10*E10 -> 7.99 | G10: 16 | H10: 0.15 | I10: =D10*G10*H10/0.6 -> 4 | J10: Y | K10: Only 16 oz goes in; rest kept.
A11: H-E-B limeade 52 oz | B11: Tequila JJ | C11: H-E-B | D11: 2 | E11: 2.48 | F11: =D11*E11 -> 4.96 | G11: 52 | H11: 0 | I11: =D11*G11*H11/0.6 -> 0 | J11: Y | K11: H-E-B
A12: H-E-B cranberry cocktail 96 oz | B12: Tequila JJ | C12: H-E-B | D12: 1 | E12: 4.28 | F12: =D12*E12 -> 4.28 | G12: 96 | H12: 0 | I12: =D12*G12*H12/0.6 -> 0 | J12: Y | K12: https://www.heb.com/product-detail/h-e-b-cranberry-cocktail-juice/5785031
A13: Sprite 2 L | B13: Tequila JJ | C13: H-E-B | D13: 1 | E13: 2.97 | F13: =D13*E13 -> 2.97 | G13: 67.6 | H13: 0 | I13: =D13*G13*H13/0.6 -> 0 | J13: Y | K13: H-E-B
A14: BeatBox Party Box 6 × 500 ml | B14: Cans | C14: H-E-B | D14: 6 | E14: 3.4967 | F14: =D14*E14 -> 20.9802 | G14: 16.9 | H14: 0.111 | I14: =D14*G14*H14/0.6 -> 18.759 | J14: Y | K14: https://www.heb.com/product-detail/beatbox-party-box-variety-pack/5508020
A15: BuzzBallz Chiller 187 ml | B15: Cans | C15: H-E-B | D15: 12 | E15: 3.12 | F15: =D15*E15 -> 37.44 | G15: 6.3 | H15: 0.15 | I15: =D15*G15*H15/0.6 -> 18.9 | J15: Y | K15: https://www.heb.com/product-detail/buzzballz-sour-apple-chiller/2787503 (ABV assumed 15%)
A16: White Claw variety 24 pk | B16: Cans | C16: H-E-B | D16: 24 | E16: 1.2446 | F16: =D16*E16 -> 29.8704 | G16: 12 | H16: 0.05 | I16: =D16*G16*H16/0.6 -> 24 | J16: Y | K16: https://www.heb.com/product-detail/white-claw-hard-seltzer-variety-24-pk-cans/3758568
... A18: Jinro Chamisul Fresh soju 750 ml | B18: he/they rider | C18: Twin Liquors | D18: 1 | E18: 11.99 | F18: =D18*E18 -> 11.99 | G18: 25.4 | H18: 0.165 | I18: =D18*G18*H18/0.6 -> 6.985 | J18: N | K18: For the b2b, not guests.
A19: Drinks total | F19: =SUM(F5:F18) -> 211.5896 | I19: =SUMIF(J5:J18,"Y",I5:I18) -> 169.79233
A21: Batch check
A22: Vodka JJ volume (gal) | B22: =SUMPRODUCT((B5:B18="Vodka JJ")*D5:D18*G5:G18)/128 -> 2.490625
A23: Vodka JJ strength | B23: =SUMPRODUCT((B5:B18="Vodka JJ")*D5:D18*G5:G18*H5:H18)/(B22*128) -> 0.074278545
A24: Tequila JJ volume (gal) | B24: =SUMPRODUCT((B5:B18="Tequila JJ")*D5:D18*G5:G18)/128 -> 2.678125
A25: Tequila JJ strength | B25: =SUMPRODUCT((B5:B18="Tequila JJ")*D5:D18*G5:G18*H5:H18)/(B24*128) -> 0.076079347
A26: Serve: 1 std drink of JJ ≈ oz | B26: =0.6/AVERAGE(B23,B25) -> 7.9809579 | C26: → an 8 oz pour in a 16 oz cup over ice ≈ 1 drink
A28: Do we have enough?
A29: Drinking guests | B29: 55 | C29: 70 cap; BYOB, so not everyone drinks ours
A30: Drinks each from us | B30: 3
A31: Needed | B31: =B29*B30 -> 165
A32: We have | B32: =I19 -> 169.79233
A33: Covered | B33: =I19/B31 -> 1.0290444
A34: Cost per std drink | B34: =SUMIF(J5:J18,"Y",F5:F18)/I19 -> 1.1755513
A36: Backup if JJ runs dry: second vodka batch ≈ $29, second tequila batch ≈ $49 (same recipe).
A37: Texas: spirits only at package stores (Twin, Spec's, WB Liquors at Costco Kelly Ln), Mon–Sat 10am–9pm, closed Sun. Buy liquor by Thu 29 Oct; grocery stuff any day.

Sheet Ice & Cups
A1: Ice, cups, serving
A2: Prices seen 5 Oct 2026. Pick = the one that goes into the budget (Y/N).
A4: Ice needed (lb) | B4: 160 | C4: ≈ 1 lb per guest for cups + ~90 lb for the cooler/tubs over 5 hours
A6: Ice source | B6: Where | C6: lb / bag | D6: $ / bag | E6: $ / lb | F6: Bags | G6: Cost | H6: Pick? · note
A7: Texas Cold Front ice house (Twice the Ice) | B7: 448 FM 685 / 15803 Windermere Dr, Pflugerville · 24/7 | C7: 20 | D7: 3 | E7: =D7/C7 -> 0.15 | F7: =ROUNDUP($B$4/C7,0) -> 8 | G7: =F7*D7 -> 24 | H7: Y | I7: EST $3/20 lb (typical TTI price) — check with free first bag, code FREEICE. tticlub.com/TexasColdFront
A8: Walmart bagged ice | B8: Pflugerville Walmart | C8: 10 | D8: 1.88 | E8: =D8/C8 -> 0.188 | F8: =ROUNDUP($B$4/C8,0) -> 16 | G8: =F8*D8 -> 30.08 | H8: N | I8: Confirmed price. Backup.
A9: Twin Liquors 20 lb | B9: 1700 E Palm Valley, Round Rock | C9: 20 | D9: 4.49 | E9: =D9/C9 -> 0.2245 | F9: =ROUNDUP($B$4/C9,0) -> 8 | G9: =F9*D9 -> 35.92 | H9: N | I9: twinliquors.com
A10: H-E-B bagged ice | B10: any H-E-B | C10: 10 | D10: 2.5 | E10: =D10/C10 -> 0.25 | F10: =ROUNDUP($B$4/C10,0) -> 16 | G10: =F10*D10 -> 40 | H10: N
A11: Artic Refresh kiosk | B11: several Austin kiosks · 24/7 | C11: 10 | D11: 3 | E11: =D11/C11 -> 0.3 | F11: =ROUNDUP($B$4/C11,0) -> 16 | G11: =F11*D11 -> 48 | H11: N | I11: articrefresh.com
A14: Cups needed | B14: 250 | C14: ≈ 3.5 per guest (people lose cups)
A16: Clear 16 oz cups | B16: Store | C16: Per pack | D16: $ / pack | E16: $ / cup | F16: Packs | G16: Cost | H16: Pick? · note
A17: Member's Mark clear 16 oz | B17: Sam's Club | C17: 132 | D17: 11.28 | E17: =D17/C17 -> 0.085454545 | F17: =ROUNDUP($B$14/C17,0) -> 2 | G17: =F17*D17 -> 22.56 | H17: Y | I17: https://www.samsclub.com/p/members-mark-clear-plastic-cups-16oz-132ct/prod13710456
A18: Great Value clear 16 oz | B18: Walmart | C18: 100 | D18: 8.98 | E18: =D18/C18 -> 0.0898 | F18: =ROUNDUP($B$14/C18,0) -> 3 | G18: =F18*D18 -> 26.94 | H18: N | I18: Same-day pickup. https://www.walmart.com/ip/28212763
A19: Choice clear PET 16 oz, case | B19: WebstaurantStore | C19: 1000 | D19: 57.99 | E19: =D19/C19 -> 0.05799 | F19: =ROUNDUP($B$14/C19,0) -> 1 | G19: =F19*D19 -> 57.99 | H19: N | I19: Cheapest per cup + shipping; 750 left for future MOTION nights
A20: H-E-B clear 18 oz | B20: H-E-B | C20: 120 | D20: 11.48 | E20: =D20/C20 -> 0.095666667 | F20: =ROUNDUP($B$14/C20,0) -> 3 | G20: =F20*D20 -> 34.44 | H20: N | I20: 18 oz
A21: True clear 16 oz | B21: Target | C21: 50 | D21: 16.09 | E21: =D21/C21 -> 0.3218 | F21: =ROUNDUP($B$14/C21,0) -> 5 | G21: =F21*D21 -> 80.45 | H21: N | I21: Too expensive
A24: Other serving | B24: Store | C24: Qty | D24: $ each | G24: Cost | H24: Pick? · note
A25: Bottled water 24-pack | B25: H-E-B | C25: 2 | D25: 3.27 | G25: =C25*D25 -> 6.54 | H25: Y | I25: https://www.heb.com/product-detail/1042431
A26: Napkins 500 ct | B26: H-E-B | C26: 1 | D26: 3.48 | G26: =C26*D26 -> 3.48 | H26: Y | I26: https://www.heb.com/product-detail/645601
A27: 2 gal glass dispenser (one per JJ) | B27: Target · Threshold | C27: 2 | D27: 29.75 | G27: =C27*D27 -> 59.5 | H27: Y | I27: Mix each JJ in a bucket/cooler, refill the dispenser
A28: 3 gal acrylic dispenser, ice core | B28: WebstaurantStore | C28: 2 | D28: 42.99 | G28: =C28*D28 -> 85.98 | H28: N | I28: Shatterproof, holds a whole batch

Sheet Decor
A1: Decor · retail vs eBay / Grailed
A2: Best price picked per item. Grailed had nothing useful (only streetwear). Order eBay by ~12 Oct to land by 27 Oct.
A4: Item | B4: Zone | C4: Retail option | D4: Retail $ | E4: eBay option | F4: eBay $ (+ship) | G4: Best $ | H4: Pick? | I4: Why / link
A5: Mirror ball 20" + motor + pin light | B5: Floor | C5: Misc Rentals, E 51st (rent) | D5: 45 | E5: EM16 16" new | F5: 149.99 | G5: =IF(AND(D5="",F5=""),0,MIN(IF(D5="",1000000000,D5),IF(F5="",1000000000,F5))) -> 45 | H5: Y | I5: Rent. eBay balls 2–4× more, no used ones. miscaustin.com
A6: Leopard throw / rug under decks | B6: Floor | C6: Garvee 5×7 rug | D6: 50.99 | E6: Leopard faux-fur throw 50×60 | F6: 22.09 | G6: =IF(AND(D6="",F6=""),0,MIN(IF(D6="",1000000000,D6),IF(F6="",1000000000,F6))) -> 22.09 | H6: Y | I6: Throw is $29 cheaper. ebay.com/itm/124847880165
A7: Gothic candelabra, 5-arm iron | B7: Bar | C7: — | E7: Vintage wrought iron 20" (used, Best Offer) | F7: 38 | G7: =IF(AND(D7="",F7=""),0,MIN(IF(D7="",1000000000,D7),IF(F7="",1000000000,F7))) -> 38 | H7: Y | I7: No retail baseline. ebay.com/itm/158261116085
A8: Black LED taper candles, 4-pk | B8: Bar | C8: Walmart | D8: 23.78 | E8: Flameless w/ timer, ships from Houston | F8: 14.99 | G8: =IF(AND(D8="",F8=""),0,MIN(IF(D8="",1000000000,D8),IF(F8="",1000000000,F8))) -> 14.99 | H8: Y | I8: ebay.com/itm/256904542238
A9: Black creepy cloth (hall windows) | B9: Witch | C9: Walmart AGCAN 197×79" | D9: 15.99 | E9: 6-pk 30×72" (ships from Israel, ~16 Oct) | F9: 17.26 | G9: =IF(AND(D9="",F9=""),0,MIN(IF(D9="",1000000000,D9),IF(F9="",1000000000,F9))) -> 15.99 | H9: Y | I9: Walmart piece is one big sheet — easier.
A10: Black eucalyptus stems | B10: Witch | C10: eBay listing from 1 Oct | D10: 30.59 | E10: No active black listing 5 Oct | G10: =IF(AND(D10="",F10=""),0,MIN(IF(D10="",1000000000,D10),IF(F10="",1000000000,F10))) -> 30.59 | H10: Y | I10: Or green stems $20.69 + black spray paint
A11: Red filament bulbs, 2-pk | B11: Witch | C11: Home Depot · Sunlite | D11: 14.99 | E11: — | G11: =IF(AND(D11="",F11=""),0,MIN(IF(D11="",1000000000,D11),IF(F11="",1000000000,F11))) -> 14.99 | H11: Y | I11: homedepot.com
A12: Ornate antique-black frame 18×24 | B12: Walls | C12: Target · Craig Frames | D12: 60.99 | E12: None that size | G12: =IF(AND(D12="",F12=""),0,MIN(IF(D12="",1000000000,D12),IF(F12="",1000000000,F12))) -> 60.99 | H12: N | I12: Skip unless Open Canopy art needs it
A13: 24" round baroque mirror, black | B13: Walls | C13: Walmart · YIDIE | D13: 55.99 | E13: 28" black $111.14 | F13: 111.14 | G13: =IF(AND(D13="",F13=""),0,MIN(IF(D13="",1000000000,D13),IF(F13="",1000000000,F13))) -> 55.99 | H13: N | I13: Thrift first (Uncommon Objects, Top Drawer)
A14: Decor (picked) | G14: =SUMIF(H5:H13,"Y",G5:G13) -> 181.65
A16: Free: borrow 2–3 pieces from local artists (Open Canopy contacts) for wall credit + IG tag + invite.
A17: eBay delivery dates were quoted to an Ohio ZIP; all active listings showed 7–17 Oct, so Austin should be similar.

Sheet DIY (Maker)
A1: Make it ourselves
A2: UT Libraries Foundry (Fine Arts Library 3.200) = free for UT students/staff, cert needed per machine. Call (512) 495-4481 for print costs.
A4: Make | B4: Where | C4: Machine | D4: Est. materials $ | E4: Pick? | F4: Notes
A5: Eye triptych, 3 × 24×36 posters | B5: UT Foundry | C5: Large-format printer | D5: 30 | E5: Y | F5: EST — Foundry print cost not posted. FedEx Guadalupe is the paid backup.
A6: MOTION acrylic logo sign | B6: UT Foundry or Texas Inventionworks | C6: Laser cutter | D6: 20 | E6: Y | F6: EST — one 12×24 black or clear acrylic sheet.
A7: "VODKA" / "TEQUILA" dispenser labels | B7: Texas Inventionworks | C7: Vinyl / sticker machine | D7: 5 | E7: Y | F7: EST. Bodoni, ice blue + red.
A8: Smoking-area sign 5×7 | B8: UT Foundry / any printer | C8: Printer or laser | D8: 3 | E8: Y | F8: EST. Flyer font.
A9: Cap 01 side eyes as patches | B9: UT Foundry | C9: Baby Lock embroidery (flat) | D9: 15 | E9: N | F9: EST. No cap frame — stitch eyes flat on twill, cut, sew/heat-press on. Only if we go DIY caps.
A10: DIY (picked) | D10: =SUMIF(E5:E9,"Y",D5:D9) -> 58
A12: Other spaces: Asmbly (9701 Dessau Rd, near Pflugerville) $95/mo, laser + vinyl + Brother SE600 (4×4" max). APL Central: 3D print only.

Sheet Smoking
A1: Balcony smoking spot
A2: 21+ only (TX). We can hand out free to 21+ guests — we can't sell. Check the Rio lease allows balcony smoking.
A4: Item | B4: Store | C4: Qty | D4: $ each | E4: Cost | F4: Notes
A5: Cigarettes, pack (e.g. Marlboro) | B5: any gas station / H-E-B | C5: 2 | D5: 9.5 | E5: =C5*D5 -> 19 | F5: EST — Austin ≈ $9–10/pack (WPR $10.04 TX avg, Jan 2026)
A6: BIC Maxi lighters, 5-pk | B6: Walmart | C6: 1 | D6: 5.44 | E6: =C6*D6 -> 5.44 | F6: https://www.walmart.com/ip/24705330
A7: Windproof lidded ashtray, black | B7: Walmart · XTORKIT | C7: 1 | D7: 11.82 | E7: =C7*D7 -> 11.82 | F7: Beat eBay ($31.40)
A8: Sand bucket for butts (backup) | B8: any | C8: 1 | D8: 0 | E8: =C8*D8 -> 0 | F8: Use a spare can + sand/water
A9: Smoking total | E9: =SUM(E5:E8) -> 36.26

Sheet Hats
A1: Cap 01 · 24 caps, front logo + side eyes
A2: Blank: District DT600 distressed dad hat $6.61 (Blankstyle, $100+ cart). Need caps by Wed 28 Oct — order by ~12 Oct.
A4: Caps | B4: 24
A5: DT600 blank $ | B5: 6.61
A7: Route | B7: Embroidery / cap | C7: Side / cap | D7: Blank / cap | E7: One-time $ | F7: Total | G7: Per cap | H7: Turnaround · notes
A8: Printful (Yupoong 6245CM) | B8: 14.94 | C8: 2.95 | D8: 0 | E8: 0 | F8: =IF(B8="","quote",(B8+C8+D8)*$B$4+E8) -> 429.36 | G8: =IF(B8="","quote",F8/$B$4) -> 17.89 | H8: 2–5 biz days + ship. Blank included. Order 25 → digitizing free; else $6.50/file. Side fee per-hat unconfirmed.
A9: Bolt Printing (VC300A) | B9: 13 | C9: 5 | D9: 0 | E9: 0 | F9: =IF(B9="","quote",(B9+C9+D9)*$B$4+E9) -> 432 | G9: =IF(B9="","quote",F9/$B$4) -> 18 | H9: 9–14 biz days (tight). Front incl. digitizing ≤8k stitches; side is EST — quote.
A10: Neatko, Leander (local) | B10: 20 | C10: 20 | D10: =$B$5 -> 6.61 | E10: 0 | F10: =IF(B10="","quote",(B10+C10+D10)*$B$4+E10) -> 1118.64 | G10: =IF(B10="","quote",F10/$B$4) -> 46.61 | H10: 5–7 biz days. $15–25 per placement (midpoint used). No minimum. Quote: neatko.com/quote
A11: Austin Print Co, Cedar Park (local) | D11: =$B$5 -> 6.61 | E11: 0 | F11: =IF(B11="","quote",(B11+C11+D11)*$B$4+E11) -> quote | G11: =IF(B11="","quote",F11/$B$4) -> quote | H11: Quote needed: (512) 200-2556. Digitizing incl., no setup fee, 'a few days'.
A12: DIY patches at UT Foundry | B12: 0 | C12: 0 | D12: =$B$5 -> 6.61 | E12: 30 | F12: =IF(B12="","quote",(B12+C12+D12)*$B$4+E12) -> 188.64 | G12: =IF(B12="","quote",F12/$B$4) -> 7.86 | H12: EST materials. Labour is ours. Eyes simplified to 2–3 tones.
A14: Pick route (row name) | B14: Printful (Yupoong 6245CM)
A15: Hats cost | B15: =IFERROR(INDEX(F8:F12,MATCH(B14,A8:A12,0))+0,0) -> 429.36
A17: Halftone eyes won't stitch clean at 2.75×1.5" — simplify to 2–3 flat tones or bold line art before digitizing.
A18: Colourway still open: dusty rose vs plum / moss / oxblood vs black. If you sell caps, the price covers this line.

Sheet Shopping Run
A1: Who buys what, where, when
A2: Liquor stores close 9 PM and all day Sunday.
A4: When | B4: Where | C4: What
A5: This week | B5: eBay | C5: Candelabra (Best Offer $30), LED tapers $14.99, leopard throw $22.09
A6: This week | B6: Hats | C6: Quotes from Austin Print Co + Neatko today; Printful order of 25 as backup by ~12 Oct
A7: By 14 Oct | B7: Online (Walmart / Target) | C7: Creepy cloth, dispensers ×2, ashtray; Home Depot red bulbs
A8: By 23 Oct | B8: UT Foundry / Inventionworks | C8: Print triptych posters, cut acrylic sign, vinyl dispenser labels, smoking sign
A9: Week of 26 Oct | B9: Misc Rentals, 1901 E 51st | C9: Reserve + pick up 20" mirror ball kit ($45)
A10: Thu 29 Oct | B10: Twin Liquors / WB Liquors (Costco Kelly Ln) | C10: Svedka 1.75, Lunazul 1.75, DeKuyper triple sec, soju
A11: Thu 29 Oct | B11: H-E-B | C11: Hawaiian Punch, pineapple, Sprite ×2, limeade ×2, cranberry, BeatBox, BuzzBallz ×12, White Claw 24, water, napkins, lighters
A12: Thu 29 Oct | B12: Walmart + Sam's Club | C12: Miller Lite 30, cups 2 × 132
A13: Fri 30 Oct, afternoon | B13: Texas Cold Front ice house, Pflugerville (24/7) | C13: ~160 lb ice (Walmart backup). Cigarettes on the way.
A14: Fri 30 Oct, 6 PM | B14: Rio | C14: Mix both JJs in clean buckets/coolers, chill; label dispensers

Sheet Sources
A1: Sources
A2: Prices are listings seen on these pages 1–5 Oct 2026; re-check at checkout.
A4: Ice: tticlub.com/TexasColdFront · articrefresh.com/ice-vending-machine · twinliquors.com (20 lb ice) · reddyice.com/locations/austin-301
A5: Cups: samsclub.com prod13710456 · walmart.com/ip/28212763 · webstaurantstore.com 500CC16 · heb.com 2812012 · target.com A-90367920
A6: eBay: itm 158261116085, 124847880165, 256904542238, 297101089464, 306980432913, 166387828199, 188940592615, 198665930673
A7: Hats: blankstyle.com (DT600, 6245CM) · help.printful.com (digitization fees, fulfillment time) · stylefactoryproductions.com/blog/printful-pricing · boltprinting.com · neatko.com · austinprintco.com/custom-hats-austin · logostore.org
A8: Maker: lib.utexas.edu/visit-us/library-spaces/foundry · guides.lib.utexas.edu/Foundry/SewingAndTextiles · inventionworks.engr.utexas.edu · asmbly.org/space
A9: Smoking: comptroller.texas.gov/taxes/tobacco/faq-reg.php · worldpopulationreview.com/state-rankings/cigarette-prices-by-state · walmart.com/ip/24705330
A10: Drinks: twinliquors.com (Svedka, Lunazul, DeKuyper, soju) · heb.com (BeatBox 5508020, BuzzBallz 2787503, White Claw 3758568, cranberry 5785031) · walmart.com/ip/10984520 (Miller Lite)
