Workbook

Sheet Plan
A1: Devil's Night · drinks plan
A2: Fri 30 Oct 2026, 9 PM–2 AM. Change the yellow cells; everything else updates.
A4: Headcount
A5: Guests (incl. crew) | B5: 70
A6: Drinkers (21+, drinking) | B6: 60
A7: Drinks each (target) | B7: 3
A8: Buffer so we don't run out | B8: 0.15
A10: Do we have enough?
A11: Standard drinks needed | B11: =B6*B7*(1+B8) -> 207
A12: Standard drinks planned (guests) | B12: ='Shopping List'!L21 -> 218.06733
A13: Drinks per drinker | B13: =IFERROR(B12/B6,0) -> 3.6344556
A14: Status | B14: =IF(B12>=B11,"Enough",IF(B12>=B6*B7,"Enough, no buffer","Short by "&TEXT(B11-B12,"0")&" drinks")) -> Enough
A16: Cost
A17: Drinks total (before tax) | B17: ='Shopping List'!I21 -> 320.8
A18: Cost per guest drink | B18: ='Shopping List'!M21 -> 1.4711053
A19: Cost per guest | B19: =IFERROR(B17/B5,0) -> 4.5828571
A21: Event budget
A22: Crew members | B22: 6
A23: Each pays | B23: 176
A24: Budget | B24: =B22*B23 -> 1056
A25: he/they (co.b_nguyen b2b Nioon) | B25: 300
A26: Drinks | B26: =B17 -> 320.8
A27: Decor (lean cart) | B27: 153
A28: Mirror ball rental | B28: 45 | C28: Fill in once he quotes
A29: Rohan Rali | B29: 0 | C29: Pizza or snacks, recommended
A30: Food | B30: 0
A31: Left | B31: =B24-SUM(B25:B30) -> 237.2
A33: Where to buy
A34: Twin Liquors (or WB Liquors at Costco, Kelly Ln): the punch spirit, triple sec, tequila, soju, Cutwater. Liquor stores: Mon–Sat 10am–9pm, closed Sunday.
A35: H-E-B: cranberry, limes, club soda, water, napkins, BeatBox, BuzzBallz, White Claw (beer, wine and malt drinks are sold in grocery stores).
A36: Walmart: Miller Lite 30-pack and ice. Sam's Club: cups.
A37: Buy ice on Friday afternoon. Everything else any weekday before.

Sheet Shopping List
A1: Shopping list
A2: Yellow Qty cells are yours to change. Punch rows follow the Punch tab. Prices and ABV come from Price Compare (green) or are typed here (blue).
A4: Item | B4: Store | C4: Group | D4: Units / pack | E4: oz / unit | F4: ABV | G4: Qty | H4: Unit price | I4: Cost | J4: Standard drinks | K4: For guests? | L4: Guest drinks | M4: $ per drink
A5: =Punch!B6&" (1.75 L or as listed)" -> Everclear 190 (1.75 L or as listed) | B5: =INDEX('Price Compare'!$C$5:$C$38,MATCH(Punch!B6,'Price Compare'!$B$5:$B$38,0)) -> Twin Liquors (Round Rock) | C5: Punch | D5: 1 | E5: =Punch!B13 -> 59.2 | F5: =Punch!B12 -> 0.95 | G5: =Punch!B32 -> 1 | H5: =Punch!B14 -> 37.99 | I5: =G5*H5 -> 37.99 | J5: =IF(D5="",0,G5*D5*E5*F5/0.6) -> 93.733333 | K5: Y | L5: =Punch!B37 -> 100.5 | M5: =IFERROR(I5/J5,0) -> 0.40529872
A6: ='Price Compare'!B16 -> DeKuyper Triple Sec | B6: ='Price Compare'!C16 -> Twin Liquors (Round Rock) | C6: Punch | D6: ='Price Compare'!E16 -> 1 | E6: ='Price Compare'!F16 -> 33.8 | F6: ='Price Compare'!G16 -> 0.15 | G6: =Punch!B33 -> 1 | H6: ='Price Compare'!H16 -> 7.99 | I6: =G6*H6 -> 7.99 | J6: =IF(D6="",0,G6*D6*E6*F6/0.6) -> 8.45 | K6: N | L6: =IF(K6="Y",J6,0) -> 0 | M6: =IFERROR(I6/J6,0) -> 0.94556213
A7: ='Price Compare'!B19 -> Exotico Blanco tequila | B7: ='Price Compare'!C19 -> Twin Liquors (Round Rock) | C7: Shots | D7: ='Price Compare'!E19 -> 1 | E7: ='Price Compare'!F19 -> 25.4 | F7: ='Price Compare'!G19 -> 0.4 | G7: 1 | H7: ='Price Compare'!H19 -> 22.99 | I7: =G7*H7 -> 22.99 | J7: =IF(D7="",0,G7*D7*E7*F7/0.6) -> 16.933333 | K7: Y | L7: =IF(K7="Y",J7,0) -> 16.933333 | M7: =IFERROR(I7/J7,0) -> 1.3576772
A8: ='Price Compare'!B23 -> Jinro Chamisul Fresh soju | B8: ='Price Compare'!C23 -> Twin Liquors (Round Rock) | C8: he/they rider | D8: ='Price Compare'!E23 -> 1 | E8: ='Price Compare'!F23 -> 25.4 | F8: ='Price Compare'!G23 -> 0.165 | G8: 1 | H8: ='Price Compare'!H23 -> 11.99 | I8: =G8*H8 -> 11.99 | J8: =IF(D8="",0,G8*D8*E8*F8/0.6) -> 6.985 | K8: N | L8: =IF(K8="Y",J8,0) -> 0 | M8: =IFERROR(I8/J8,0) -> 1.7165354
A9: ='Price Compare'!B31 -> Miller Lite | B9: ='Price Compare'!C31 -> Walmart | C9: Beer | D9: ='Price Compare'!E31 -> 30 | E9: ='Price Compare'!F31 -> 12 | F9: ='Price Compare'!G31 -> 0.042 | G9: 1 | H9: ='Price Compare'!H31 -> 24.67 | I9: =G9*H9 -> 24.67 | J9: =IF(D9="",0,G9*D9*E9*F9/0.6) -> 25.2 | K9: Y | L9: =IF(K9="Y",J9,0) -> 25.2 | M9: =IFERROR(I9/J9,0) -> 0.97896825
A10: ='Price Compare'!B35 -> White Claw variety | B10: ='Price Compare'!C35 -> H-E-B | C10: Seltzer | D10: ='Price Compare'!E35 -> 24 | E10: ='Price Compare'!F35 -> 12 | F10: ='Price Compare'!G35 -> 0.05 | G10: 1 | H10: ='Price Compare'!H35 -> 29.87 | I10: =G10*H10 -> 29.87 | J10: =IF(D10="",0,G10*D10*E10*F10/0.6) -> 24 | K10: Y | L10: =IF(K10="Y",J10,0) -> 24 | M10: =IFERROR(I10/J10,0) -> 1.2445833
A11: ='Price Compare'!B24 -> BeatBox Party Box variety | B11: ='Price Compare'!C24 -> H-E-B | C11: Ready to drink | D11: ='Price Compare'!E24 -> 6 | E11: ='Price Compare'!F24 -> 16.9 | F11: ='Price Compare'!G24 -> 0.111 | G11: 1 | H11: ='Price Compare'!H24 -> 20.98 | I11: =G11*H11 -> 20.98 | J11: =IF(D11="",0,G11*D11*E11*F11/0.6) -> 18.759 | K11: Y | L11: =IF(K11="Y",J11,0) -> 18.759 | M11: =IFERROR(I11/J11,0) -> 1.1183965
A12: ='Price Compare'!B26 -> Cutwater Lime Margarita | B12: ='Price Compare'!C26 -> Twin Liquors (Round Rock) | C12: Ready to drink | D12: ='Price Compare'!E26 -> 4 | E12: ='Price Compare'!F26 -> 12 | F12: ='Price Compare'!G26 -> 0.125 | G12: 2 | H12: ='Price Compare'!H26 -> 12.99 | I12: =G12*H12 -> 25.98 | J12: =IF(D12="",0,G12*D12*E12*F12/0.6) -> 20 | K12: Y | L12: =IF(K12="Y",J12,0) -> 20 | M12: =IFERROR(I12/J12,0) -> 1.299
A13: ='Price Compare'!B27 -> BuzzBallz Biggie Chiller | B13: ='Price Compare'!C27 -> H-E-B | C13: Ready to drink | D13: ='Price Compare'!E27 -> 1 | E13: ='Price Compare'!F27 -> 50.7 | F13: ='Price Compare'!G27 -> 0.15 | G13: 1 | H13: ='Price Compare'!H27 -> 17.76 | I13: =G13*H13 -> 17.76 | J13: =IF(D13="",0,G13*D13*E13*F13/0.6) -> 12.675 | K13: Y | L13: =IF(K13="Y",J13,0) -> 12.675 | M13: =IFERROR(I13/J13,0) -> 1.4011834
A14: H-E-B cranberry cocktail 96 oz | B14: H-E-B | C14: Punch mixer | F14: 0 | G14: =Punch!B34 -> 6 | H14: 4.28 | I14: =G14*H14 -> 25.68 | J14: =IF(D14="",0,G14*D14*E14*F14/0.6) -> 0 | K14: - | L14: =IF(K14="Y",J14,0) -> 0 | M14: =IFERROR(I14/J14,0) -> 0
A15: Limes | B15: H-E-B | C15: Punch mixer | F15: 0 | G15: =Punch!B35 -> 88 | H15: 0.2 | I15: =G15*H15 -> 17.6 | J15: =IF(D15="",0,G15*D15*E15*F15/0.6) -> 0 | K15: - | L15: =IF(K15="Y",J15,0) -> 0 | M15: =IFERROR(I15/J15,0) -> 0
A16: Club soda 2 L | B16: H-E-B | C16: Punch mixer | F16: 0 | G16: =Punch!B36 -> 4 | H16: 1.78 | I16: =G16*H16 -> 7.12 | J16: =IF(D16="",0,G16*D16*E16*F16/0.6) -> 0 | K16: - | L16: =IF(K16="Y",J16,0) -> 0 | M16: =IFERROR(I16/J16,0) -> 0
A17: Ice 10 lb bag (buy Friday) | B17: Walmart | C17: Supplies | F17: 0 | G17: 20 | H17: 1.88 | I17: =G17*H17 -> 37.6 | J17: =IF(D17="",0,G17*D17*E17*F17/0.6) -> 0 | K17: - | L17: =IF(K17="Y",J17,0) -> 0 | M17: =IFERROR(I17/J17,0) -> 0
A18: Bottled water 24-pack | B18: H-E-B | C18: Supplies | F18: 0 | G18: 2 | H18: 3.27 | I18: =G18*H18 -> 6.54 | J18: =IF(D18="",0,G18*D18*E18*F18/0.6) -> 0 | K18: - | L18: =IF(K18="Y",J18,0) -> 0 | M18: =IFERROR(I18/J18,0) -> 0
A19: Clear 16 oz cups, 132 ct | B19: Sam's Club | C19: Supplies | F19: 0 | G19: 2 | H19: 11.28 | I19: =G19*H19 -> 22.56 | J19: =IF(D19="",0,G19*D19*E19*F19/0.6) -> 0 | K19: - | L19: =IF(K19="Y",J19,0) -> 0 | M19: =IFERROR(I19/J19,0) -> 0
A20: Napkins 500 ct | B20: H-E-B | C20: Supplies | F20: 0 | G20: 1 | H20: 3.48 | I20: =G20*H20 -> 3.48 | J20: =IF(D20="",0,G20*D20*E20*F20/0.6) -> 0 | K20: - | L20: =IF(K20="Y",J20,0) -> 0 | M20: =IFERROR(I20/J20,0) -> 0
A21: Total | I21: =SUM(I5:I20) -> 320.8 | J21: =SUM(J5:J20) -> 226.73567 | L21: =SUM(L5:L20) -> 218.06733 | M21: =IFERROR(I21/L21,0) -> 1.4711053
A22: Prices before tax. Twin Liquors prices are the Round Rock store; H-E-B prices may come from a non-Austin default store. Soju is for he/they and isn't counted in guest drinks.
A23: Punch row: guest drinks = what the punch batch holds (spirit + triple sec), so leftover spirit isn't counted.
A25: By group
A26: Group | I26: Cost | L26: Guest drinks
A27: Punch | I27: =SUMIFS($I$5:$I$20,$C$5:$C$20,A27) -> 45.98 | L27: =SUMIFS($L$5:$L$20,$C$5:$C$20,A27) -> 100.5
A28: Punch mixer | I28: =SUMIFS($I$5:$I$20,$C$5:$C$20,A28) -> 50.4 | L28: =SUMIFS($L$5:$L$20,$C$5:$C$20,A28) -> 0
A29: Shots | I29: =SUMIFS($I$5:$I$20,$C$5:$C$20,A29) -> 22.99 | L29: =SUMIFS($L$5:$L$20,$C$5:$C$20,A29) -> 16.933333
A30: Beer | I30: =SUMIFS($I$5:$I$20,$C$5:$C$20,A30) -> 24.67 | L30: =SUMIFS($L$5:$L$20,$C$5:$C$20,A30) -> 25.2
A31: Seltzer | I31: =SUMIFS($I$5:$I$20,$C$5:$C$20,A31) -> 29.87 | L31: =SUMIFS($L$5:$L$20,$C$5:$C$20,A31) -> 24
A32: Ready to drink | I32: =SUMIFS($I$5:$I$20,$C$5:$C$20,A32) -> 64.72 | L32: =SUMIFS($L$5:$L$20,$C$5:$C$20,A32) -> 51.434
A33: he/they rider | I33: =SUMIFS($I$5:$I$20,$C$5:$C$20,A33) -> 11.99 | L33: =SUMIFS($L$5:$L$20,$C$5:$C$20,A33) -> 0
A34: Supplies | I34: =SUMIFS($I$5:$I$20,$C$5:$C$20,A34) -> 70.18 | L34: =SUMIFS($L$5:$L$20,$C$5:$C$20,A34) -> 0

Sheet Punch
A1: Devil's Night punch
A2: Change the yellow cells. The base spirit list comes from Price Compare; the recipe keeps the same alcohol per gallon whichever spirit you pick.
A4: Punch gallons | B4: 6 | C4: How many gallons of punch over the night (2 at doors, then refills).
A5: 0.0 (no alcohol) gallons | B5: 1
A6: Base spirit | B6: Everclear 190 | C6: Pick from the list. Svedka/Smirnoff cost almost the same per drink and are far safer to pour.
A7: Pure alcohol per gallon (oz) | B7: 9.3 | C7: 9.3 oz = about 23 oz of 80-proof vodka or 9.8 oz of Everclear per gallon.
A8: Triple sec per gallon (oz) | B8: 5 | C8: DeKuyper, 15% ABV.
A9: Cranberry per gallon (oz) | B9: 64 | C9: H-E-B cranberry cocktail.
A10: Lime juice per gallon (oz) | B10: 12 | C10: About 12 limes.
A11: Calculated
A12: Base spirit ABV | B12: =INDEX('Price Compare'!$G$5:$G$38,MATCH(B6,'Price Compare'!$B$5:$B$38,0)) -> 0.95
A13: Base spirit bottle size (oz) | B13: =INDEX('Price Compare'!$F$5:$F$38,MATCH(B6,'Price Compare'!$B$5:$B$38,0)) -> 59.2
A14: Base spirit bottle price | B14: =INDEX('Price Compare'!$H$5:$H$38,MATCH(B6,'Price Compare'!$B$5:$B$38,0)) -> 37.99
A15: Base spirit per gallon (oz) | B15: =B7/B12 -> 9.7894737
A16: Club soda per gallon (oz) | B16: =128-B15-B8-B9-B10 -> 37.210526
A17: Punch ABV | B17: =(B15*B12+B8*0.15)/128 -> 0.078515625
A18: Standard drinks per gallon | B18: =(B15*B12+B8*0.15)/0.6 -> 16.75
A19: 9 oz cup = standard drinks | B19: =9*B17/0.6 -> 1.1777344
A21: Recipe per gallon (128 oz)
A22: Base spirit | B22: =B15 -> 9.7894737 | C22: oz
A23: Triple sec | B23: =B8 -> 5 | C23: oz
A24: Cranberry juice cocktail | B24: =B9 -> 64 | C24: oz
A25: Fresh lime juice | B25: =B10 -> 12 | C25: oz
A26: Club soda (add when serving) | B26: =B16 -> 37.210526 | C26: oz
A27: Total | B27: =SUM(B22:B26) -> 128 | C27: oz
A29: 0.0 per gallon: cranberry 80 oz, lime 16 oz, club soda 32 oz.
A31: Batch totals (feed the Shopping List)
A32: Base spirit bottles | B32: =ROUNDUP(B4*B15/B13,0) -> 1
A33: Triple sec 1 L bottles | B33: =ROUNDUP(B4*B8/33.8,0) -> 1
A34: Cranberry 96 oz jugs (incl. 1 spare) | B34: =ROUNDUP((B4*B9+B5*80)/96,0)+1 -> 6
A35: Limes (about 1 oz each) | B35: =ROUNDUP(B4*B10+B5*16,0) -> 88
A36: Club soda 2 L bottles | B36: =ROUNDUP((B4*B16+B5*32)/67.6,0) -> 4
A37: Punch standard drinks | B37: =B4*B18 -> 100.5

Sheet Price Compare
A1: Price Compare · alcohol, checked 5 Oct 2026
A2: Blue = typed-in price or ABV (edit if the shelf differs). Black = calculated. Standard drink = 0.6 oz of pure alcohol (US).
A4: Category | B4: Product | C4: Store | D4: Size | E4: Units / pack | F4: oz / unit | G4: ABV | H4: Price | I4: Standard drinks / pack | J4: $ per standard drink | K4: Notes | L4: Source
A5: Punch base | B5: Everclear 190 | C5: Twin Liquors (Round Rock) | D5: 1.75 L | E5: 1 | F5: 59.2 | G5: 0.95 | H5: 37.99 | I5: =E5*F5*G5/0.6 -> 93.733333 | J5: =IFERROR(H5/I5,0) -> 0.40529872 | K5: Cheapest per drink. 95% alcohol: jigger only, flammable, never as shots. | L5: https://twinliquors.com/shop/product/everclear-190/56caaf6e7562752ed5441600
A6: Punch base | B6: Everclear 190 (750 ml) | C6: Twin Liquors (Round Rock) | D6: 750 ml | E6: 1 | F6: 25.4 | G6: 0.95 | H6: 18.99 | I6: =E6*F6*G6/0.6 -> 40.216667 | J6: =IFERROR(H6/I6,0) -> 0.47219229 | K6: Worse value than the 1.75 L. | L6: https://twinliquors.com/shop/product/everclear-190/56caaf777562752ed5461600
A7: Punch base | B7: Svedka | C7: Twin Liquors (Round Rock) | D7: 1.75 L | E7: 1 | F7: 59.2 | G7: 0.4 | H7: 18.99 | I7: =E7*F7*G7/0.6 -> 39.466667 | J7: =IFERROR(H7/I7,0) -> 0.48116554 | K7: Best-value vodka. Clean in punch, much safer to pour than Everclear. | L7: https://twinliquors.com/shop/product/svedka-80-proof-vodka/564bd7e469702d5e6e6e0000
A8: Punch base | B8: Smirnoff 80 | C8: Twin Liquors (Round Rock) | D8: 1.75 L | E8: 1 | F8: 59.2 | G8: 0.4 | H8: 19.99 | I8: =E8*F8*G8/0.6 -> 39.466667 | J8: =IFERROR(H8/I8,0) -> 0.50650338 | K8: Same tier as Svedka. | L8: https://twinliquors.com/shop/product/smirnoff-80-proof-vodka/5521cef66561310003380200
A9: Punch base | B9: New Amsterdam | C9: Twin Liquors (Round Rock) | D9: 1.75 L | E9: 1 | F9: 59.2 | G9: 0.4 | H9: 19.99 | I9: =E9*F9*G9/0.6 -> 39.466667 | J9: =IFERROR(H9/I9,0) -> 0.50650338 | K9: Same tier as Svedka. | L9: https://twinliquors.com/shop/product/new-amsterdam-80-proof-vodka/5521cef46561310003d70100
A10: Punch base | B10: Wolfschmidt | C10: Twin Liquors (Round Rock) | D10: 1.75 L | E10: 1 | F10: 59.2 | G10: 0.4 | H10: 15.49 | I10: =E10*F10*G10/0.6 -> 39.466667 | J10: =IFERROR(H10/I10,0) -> 0.39248311 | K10: Cheapest vodka; harsher. | L10: https://twinliquors.com/shop/product/wolfschmidt-80-proof-vodka/587d3b70bfb24113b11b0173
A11: Punch base | B11: Western Son | C11: Twin Liquors (Round Rock) | D11: 1.75 L | E11: 1 | F11: 59.2 | G11: 0.4 | H11: 21.99 | I11: =E11*F11*G11/0.6 -> 39.466667 | J11: =IFERROR(H11/I11,0) -> 0.55717905 | K11: Texas-made. Out of stock at Round Rock on 5 Oct. | L11: https://twinliquors.com/shop/product/western-son-vodka/5967142912f2fb071587e708
A12: Punch base | B12: Deep Eddy Original | C12: Twin Liquors (Round Rock) | D12: 1.75 L | E12: 1 | F12: 59.2 | G12: 0.4 | H12: 28.99 | I12: =E12*F12*G12/0.6 -> 39.466667 | J12: =IFERROR(H12/I12,0) -> 0.73454392 | K12: Austin-made. | L12: https://twinliquors.com/shop/product/deep-eddy-vodka-original/56caaaf37562752ed5ba1500
A13: Punch base | B13: Tito's Handmade | C13: Twin Liquors (Round Rock) | D13: 1.75 L | E13: 1 | F13: 59.2 | G13: 0.4 | H13: 32.99 | I13: =E13*F13*G13/0.6 -> 39.466667 | J13: =IFERROR(H13/I13,0) -> 0.83589527 | K13: Austin-made, best known. | L13: https://twinliquors.com/shop/product/titos-handmade-vodka/564bd96269702d5e977a0100
A14: Punch base | B14: Absolut | C14: Twin Liquors (Round Rock) | D14: 1.75 L | E14: 1 | F14: 59.2 | G14: 0.4 | H14: 29.99 | I14: =E14*F14*G14/0.6 -> 39.466667 | J14: =IFERROR(H14/I14,0) -> 0.75988176 | L14: https://twinliquors.com/shop/product/absolut-vodka/618e7c297f9199660f0132b8
A15: Punch base | B15: Bacardi Superior (rum) | C15: Twin Liquors (Round Rock) | D15: 1.75 L | E15: 1 | F15: 59.2 | G15: 0.4 | H15: 22.99 | I15: =E15*F15*G15/0.6 -> 39.466667 | J15: =IFERROR(H15/I15,0) -> 0.58251689 | K15: Rum punch option. | L15: https://twinliquors.com/shop/product/bacardi-superior-rum/587e15d239e21c07b160de8c
A16: Orange liqueur | B16: DeKuyper Triple Sec | C16: Twin Liquors (Round Rock) | D16: 1 L | E16: 1 | F16: 33.8 | G16: 0.15 | H16: 7.99 | I16: =E16*F16*G16/0.6 -> 8.45 | J16: =IFERROR(H16/I16,0) -> 0.94556213 | K16: Price from 1 Oct check. | L16: https://twinliquors.com/
A17: Orange liqueur | B17: Bols Triple Sec | C17: Twin Liquors (Round Rock) | D17: 1 L | E17: 1 | F17: 33.8 | G17: 0.21 | H17: 9.99 | I17: =E17*F17*G17/0.6 -> 11.83 | J17: =IFERROR(H17/I17,0) -> 0.84446323 | L17: https://twinliquors.com/shop/product/bols-liqueur-triple-sec-/56dd1c1a69702d1873930000
A18: Orange liqueur | B18: Patrón Citrónge | C18: Twin Liquors (Round Rock) | D18: 750 ml | E18: 1 | F18: 25.4 | G18: 0.35 | H18: 21.99 | I18: =E18*F18*G18/0.6 -> 14.816667 | J18: =IFERROR(H18/I18,0) -> 1.4841395 | K18: Upgrade. | L18: https://twinliquors.com/shop/product/patron-citronge-orange/56cacd1575627527c4200100
A19: Shots | B19: Exotico Blanco tequila | C19: Twin Liquors (Round Rock) | D19: 750 ml | E19: 1 | F19: 25.4 | G19: 0.4 | H19: 22.99 | I19: =E19*F19*G19/0.6 -> 16.933333 | J19: =IFERROR(H19/I19,0) -> 1.3576772 | K19: Price from 1 Oct check. | L19: https://twinliquors.com/
A20: Shots | B20: Familia Camarena Silver tequila | C20: Twin Liquors (Round Rock) | D20: 750 ml | E20: 1 | F20: 25.4 | G20: 0.4 | H20: 22.99 | I20: =E20*F20*G20/0.6 -> 16.933333 | J20: =IFERROR(H20/I20,0) -> 1.3576772 | K20: Same price, smoother reputation. | L20: https://twinliquors.com/shop/product/camarena-silver-tequila/56c270ca75627570b0f00100
A21: Shots | B21: Lunazul Blanco tequila | C21: Twin Liquors (Round Rock) | D21: 750 ml | E21: 1 | F21: 25.4 | G21: 0.4 | H21: 23.99 | I21: =E21*F21*G21/0.6 -> 16.933333 | J21: =IFERROR(H21/I21,0) -> 1.4167323 | L21: https://twinliquors.com/shop/product/lunazul-blanco-tequila/56c3373a69702d27edbd0400
A22: Shots | B22: Teremana Blanco tequila | C22: Twin Liquors (Round Rock) | D22: 750 ml | E22: 1 | F22: 25.4 | G22: 0.4 | H22: 29.99 | I22: =E22*F22*G22/0.6 -> 16.933333 | J22: =IFERROR(H22/I22,0) -> 1.771063 | K22: Upgrade. | L22: https://twinliquors.com/shop/product/teremana-blanco-tequila/5e696e9ce220be04a4e17255
A23: Artist | B23: Jinro Chamisul Fresh soju | C23: Twin Liquors (Round Rock) | D23: 750 ml | E23: 1 | F23: 25.4 | G23: 0.165 | H23: 11.99 | I23: =E23*F23*G23/0.6 -> 6.985 | J23: =IFERROR(H23/I23,0) -> 1.7165354 | K23: For he/they. Out of stock at Round Rock on 5 Oct. | L23: https://twinliquors.com/shop/product/jinro-chamisul-fresh-soju/5d39f1e6ec27b513fd255b65
A24: Ready to drink | B24: BeatBox Party Box variety | C24: H-E-B | D24: 6 × 500 ml | E24: 6 | F24: 16.9 | G24: 0.111 | H24: 20.98 | I24: =E24*F24*G24/0.6 -> 18.759 | J24: =IFERROR(H24/I24,0) -> 1.1183965 | K24: Wine/malt based: sold at H-E-B. | L24: https://www.heb.com/product-detail/beatbox-party-box-variety-pack/5508020
A25: Ready to drink | B25: BeatBox single | C25: Walmart | D25: 500 ml | E25: 1 | F25: 16.9 | G25: 0.111 | H25: 4.22 | I25: =E25*F25*G25/0.6 -> 3.1265 | J25: =IFERROR(H25/I25,0) -> 1.3497521 | L25: https://www.walmart.com/ip/BeatBox-Fruit-Punch-Party-Punch-Cocktail-11-1-ABV-500ml-Tetra/705837624
A26: Ready to drink | B26: Cutwater Lime Margarita | C26: Twin Liquors (Round Rock) | D26: 4 × 12 oz | E26: 4 | F26: 12 | G26: 0.125 | H26: 12.99 | I26: =E26*F26*G26/0.6 -> 10 | J26: =IFERROR(H26/I26,0) -> 1.299 | K26: Spirit based: liquor store only. | L26: https://twinliquors.com/shop/product/cutwater-lime-margarita-4pk-12oz-cans/5aee1ad65065c128fd3529da
A27: Ready to drink | B27: BuzzBallz Biggie Chiller | C27: H-E-B | D27: 1.5 L | E27: 1 | F27: 50.7 | G27: 0.15 | H27: 17.76 | I27: =E27*F27*G27/0.6 -> 12.675 | J27: =IFERROR(H27/I27,0) -> 1.4011834 | K27: Wine based: H-E-B. | L27: https://www.heb.com/product-detail/buzzballz-biggies-berry-cherry-limeade-large-chiller/15320037
A28: Ready to drink | B28: BuzzBallz Chiller single | C28: H-E-B | D28: 187 ml | E28: 1 | F28: 6.3 | G28: 0.15 | H28: 3.12 | I28: =E28*F28*G28/0.6 -> 1.575 | J28: =IFERROR(H28/I28,0) -> 1.9809524 | K28: ABV assumed 15%. | L28: https://www.heb.com/product-detail/buzzballz-sour-apple-chiller/2787503
A29: Ready to drink | B29: BuzzBallz Strawberry Rita | C29: Twin Liquors (Round Rock) | D29: 200 ml | E29: 1 | F29: 6.8 | G29: 0.15 | H29: 3.99 | I29: =E29*F29*G29/0.6 -> 1.7 | J29: =IFERROR(H29/I29,0) -> 2.3470588 | K29: Spirit based. ABV assumed 15%. | L29: https://twinliquors.com/shop/product/buzzballz-rtd-strawberry-rita/573f9d5969702d34f5453500
A30: Ready to drink | B30: High Noon vodka seltzer | C30: Twin Liquors (Round Rock) | D30: 8 × 12 oz | E30: 8 | F30: 12 | G30: 0.045 | H30: 19.99 | I30: =E30*F30*G30/0.6 -> 7.2 | J30: =IFERROR(H30/I30,0) -> 2.7763889 | K30: Spirit based. ABV assumed 4.5%. | L30: https://twinliquors.com/shop/product/high-noon-sun-sips-tropical-variety-pack-rtd-cocktail-cans/607de70b40603747fe45e498
A31: Beer | B31: Miller Lite | C31: Walmart | D31: 30 × 12 oz | E31: 30 | F31: 12 | G31: 0.042 | H31: 24.67 | I31: =E31*F31*G31/0.6 -> 25.2 | J31: =IFERROR(H31/I31,0) -> 0.97896825 | K31: Marked down from $32.49. H-E-B $25.27. | L31: https://www.walmart.com/ip/Miller-Lite-Beer-30-Pack-12-fl-oz-Aluminum-Cans-4-2-ABV-Domestic-Light-Lager/10984520
A32: Beer | B32: Lone Star | C32: H-E-B | D32: 30 × 12 oz | E32: 30 | F32: 12 | G32: 0.0465 | H32: 27.47 | I32: =E32*F32*G32/0.6 -> 27.9 | J32: =IFERROR(H32/I32,0) -> 0.98458781 | K32: ABV assumed 4.65%. | L32: https://www.heb.com/product-detail/lone-star-texas-beer-30-pk-cans/11448020
A33: Beer | B33: Michelob Ultra | C33: H-E-B | D33: 30 × 12 oz | E33: 30 | F33: 12 | G33: 0.042 | H33: 29.87 | I33: =E33*F33*G33/0.6 -> 25.2 | J33: =IFERROR(H33/I33,0) -> 1.1853175 | L33: https://www.heb.com/product-detail/michelob-ultra-superior-light-lager-beer-cans-30-pack-12-oz/1484389
A34: Beer | B34: Modelo Especial | C34: H-E-B | D34: 24 × 12 oz | E34: 24 | F34: 12 | G34: 0.044 | H34: 26.66 | I34: =E34*F34*G34/0.6 -> 21.12 | J34: =IFERROR(H34/I34,0) -> 1.2623106 | K34: ABV assumed 4.4%. | L34: https://www.heb.com/product-detail/modelo-especial-mexican-lager-import-beer-24-pk-cans/1610273
A35: Seltzer | B35: White Claw variety | C35: H-E-B | D35: 24 × 12 oz | E35: 24 | F35: 12 | G35: 0.05 | H35: 29.87 | I35: =E35*F35*G35/0.6 -> 24 | J35: =IFERROR(H35/I35,0) -> 1.2445833 | L35: https://www.heb.com/product-detail/white-claw-hard-seltzer-variety-24-pk-cans/3758568
A36: Seltzer | B36: White Claw variety (12) | C36: H-E-B | D36: 12 × 12 oz | E36: 12 | F36: 12 | G36: 0.05 | H36: 18.67 | I36: =E36*F36*G36/0.6 -> 12 | J36: =IFERROR(H36/I36,0) -> 1.5558333 | L36: https://www.heb.com/product-detail/white-claw-hard-seltzer-hard-seltzer-variety-pack-12-pk-cans-flavor-collection-no-2/3758566
A37: Seltzer | B37: Truly Originals variety | C37: H-E-B | D37: 24 × 12 oz | E37: 24 | F37: 12 | G37: 0.05 | H37: 29.48 | I37: =E37*F37*G37/0.6 -> 24 | J37: =IFERROR(H37/I37,0) -> 1.2283333 | L37: https://www.heb.com/product-detail/truly-hard-seltzer-originals-variety-24-pk-cans/3495514
A38: Seltzer | B38: Topo Chico Hard Seltzer variety | C38: H-E-B | D38: 24 × 12 oz | E38: 24 | F38: 12 | G38: 0.047 | H38: 31.98 | I38: =E38*F38*G38/0.6 -> 22.56 | J38: =IFERROR(H38/I38,0) -> 1.4175532 | L38: https://www.heb.com/product-detail/topo-chico-hard-seltzer-variety-24-pk-cans/6327581

Sheet Notes & Sources
A1: Notes & sources
A3: Standard drink: 0.6 oz (14 g) of pure alcohol, the US definition. Standard drinks = volume (oz) × ABV ÷ 0.6.
A4: Prices checked online 5 Oct 2026, before tax. Twin Liquors = Round Rock (Palm Valley) store; some H-E-B pages showed a non-Austin default store. Spec's, Total Wine and Costco didn't show Austin prices online.
A5: ABV marked with a cell comment was not on the product page; a typical value was assumed.
A6: Texas: only package stores sell spirits and spirit-based canned cocktails (Cutwater, High Noon, BuzzBallz Cocktails). Grocery stores sell beer, wine and wine/malt drinks (BeatBox, BuzzBallz Chillers, White Claw).
A7: Everclear is 95% alcohol: measure with a jigger, never serve as shots, keep away from candles and the smokers. Only the bar person handles it.
A8: No selling, no collection, IDs checked for anyone drinking. Water and food out all night; rides home only.
A9: TABC package store hours: https://www.tabc.texas.gov/static/sites/default/files/2021-08/package-store-p-and-local-distributor-lp-off-premise-retailers-lc_0.pdf
A10: Product links for every price are in the Source column of Price Compare and in cell comments on the Shopping List.
